qwertyui/__init__.py
qwertyui/backups/__init__.py
qwertyui/backups/periodic_backup_remover.py
qwertyui/backups/tests.py
qwertyui/minio/__init__.py
qwertyui/odoo/__init__.py
qwertyui-1.0.23.dist-info/METADATA
qwertyui-1.0.23.dist-info/RECORD
qwertyui-1.0.23.dist-info/WHEEL
qwertyui-1.0.23.dist-info/top_level.txt
