Metadata-Version: 2.1
Name: qwertyui
Version: 1.0.23
Summary: Some common Python functions and algorithms
Home-page: https://github.com/CGenie/qwertyui
Author: Przemyslaw Kaminski
Author-email: cgenie@gmail.com
License: UNKNOWN
Platform: UNKNOWN
Requires-Dist: minio (>=4.0.11)
Requires-Dist: requests (>=2.21.0)
Requires-Dist: requests-toolbelt (>=0.9.0)
